<item>
<title>DE: AT: ORF 1 HD</title>
<link>plugin://plugin.video.f4mTester/?url=http://212.232.29.250:8000/live/alisan1234/alisan1234/409.ts&amp;streamtype=TSDOWNLOADER&amp;name=DE: AT: ORF 1 HD</link>
</item>

<item>
<title>DE: AT: ORF 2 HD</title>
<link>plugin://plugin.video.f4mTester/?url=http://212.232.29.250:8000/live/alisan1234/alisan1234/408.ts&amp;streamtype=TSDOWNLOADER&amp;name=DE: AT: ORF 2 HD</link>
</item>

<item>
<title>DE: AT: ATV HD</title>
<link>plugin://plugin.video.f4mTester/?url=http://212.232.29.250:8000/live/alisan1234/alisan1234/2080.ts&amp;streamtype=TSDOWNLOADER&amp;name=DE: AT: ATV HD</link>
</item>

<item>
<title>DE: AT: ATV 2</title>
<link>plugin://plugin.video.f4mTester/?url=http://212.232.29.250:8000/live/alisan1234/alisan1234/2079.ts&amp;streamtype=TSDOWNLOADER&amp;name=DE: AT: ATV 2</link>
</item>

<item>
<title>DE: AT: PULS 4</title>
<link>plugin://plugin.video.f4mTester/?url=http://212.232.29.250:8000/live/alisan1234/alisan1234/405.ts&amp;streamtype=TSDOWNLOADER&amp;name=DE: AT: PULS 4</link>
</item>

<item>
<title>DE: DAS ERSTE HD</title>
<link>plugin://plugin.video.f4mTester/?url=http://212.232.29.250:8000/live/alisan1234/alisan1234/404.ts&amp;streamtype=TSDOWNLOADER&amp;name=DE: DAS ERSTE HD</link>
</item>

<item>
<title>DE: FOX HD</title>
<link>plugin://plugin.video.f4mTester/?url=http://212.232.29.250:8000/live/alisan1234/alisan1234/382.ts&amp;streamtype=TSDOWNLOADER&amp;name=DE: FOX HD</link>
</item>

<item>
<title>DE: KABEL EINS HD</title>
<link>plugin://plugin.video.f4mTester/?url=http://212.232.29.250:8000/live/alisan1234/alisan1234/381.ts&amp;streamtype=TSDOWNLOADER&amp;name=DE: KABEL EINS HD</link>
</item>

<item>
<title>DE: KABEL 1</title>
<link>plugin://plugin.video.f4mTester/?url=http://212.232.29.250:8000/live/alisan1234/alisan1234/428.ts&amp;streamtype=TSDOWNLOADER&amp;name=DE: KABEL 1</link>
</item>

<item>
<title>DE: KABEL EINS CLASSIC HD</title>
<link>plugin://plugin.video.f4mTester/?url=http://212.232.29.250:8000/live/alisan1234/alisan1234/380.ts&amp;streamtype=TSDOWNLOADER&amp;name=DE: KABEL EINS CLASSIC HD</link>
</item>

<item>
<title>DE: PROSIEBEN HD</title>
<link>plugin://plugin.video.f4mTester/?url=http://212.232.29.250:8000/live/alisan1234/alisan1234/379.ts&amp;streamtype=TSDOWNLOADER&amp;name=DE: PROSIEBEN HD</link>
</item>

<item>
<title>DE: PRO 7</title>
<link>plugin://plugin.video.f4mTester/?url=http://212.232.29.250:8000/live/alisan1234/alisan1234/421.ts&amp;streamtype=TSDOWNLOADER&amp;name=DE: PRO 7</link>
</item>

<item>
<title>DE: PRO 7 MAXX</title>
<link>plugin://plugin.video.f4mTester/?url=http://212.232.29.250:8000/live/alisan1234/alisan1234/424.ts&amp;streamtype=TSDOWNLOADER&amp;name=DE: PRO 7 MAXX</link>
</item>

<item>
<title>DE: PROSIEBEN Fun HD</title>
<link>plugin://plugin.video.f4mTester/?url=http://212.232.29.250:8000/live/alisan1234/alisan1234/377.ts&amp;streamtype=TSDOWNLOADER&amp;name=DE: PROSIEBEN Fun HD</link>
</item>

<item>
<title>DE: PROSIEBEN MAXX HD</title>
<link>plugin://plugin.video.f4mTester/?url=http://212.232.29.250:8000/live/alisan1234/alisan1234/378.ts&amp;streamtype=TSDOWNLOADER&amp;name=DE: PROSIEBEN MAXX HD</link>
</item>

<item>
<title>DE: SUPER RTL HD</title>
<link>plugin://plugin.video.f4mTester/?url=http://212.232.29.250:8000/live/alisan1234/alisan1234/389.ts&amp;streamtype=TSDOWNLOADER&amp;name=DE: SUPER RTL HD</link>
</item>

<item>
<title>DE: SuperRTL</title>
<link>plugin://plugin.video.f4mTester/?url=http://212.232.29.250:8000/live/alisan1234/alisan1234/410.ts&amp;streamtype=TSDOWNLOADER&amp;name=DE: SuperRTL</link>
</item>

<item>
<title>DE: RTL HD</title>
<link>plugin://plugin.video.f4mTester/?url=http://212.232.29.250:8000/live/alisan1234/alisan1234/396.ts&amp;streamtype=TSDOWNLOADER&amp;name=DE: RTL HD</link>
</item>

<item>
<title>DE: RTL</title>
<link>plugin://plugin.video.f4mTester/?url=http://212.232.29.250:8000/live/alisan1234/alisan1234/429.ts&amp;streamtype=TSDOWNLOADER&amp;name=DE: RTL</link>
</item>

<item>
<title>DE: RTL2 HD</title>
<link>plugin://plugin.video.f4mTester/?url=http://212.232.29.250:8000/live/alisan1234/alisan1234/395.ts&amp;streamtype=TSDOWNLOADER&amp;name=DE: RTL2 HD</link>
</item>

<item>
<title>DE: RTL2</title>
<link>plugin://plugin.video.f4mTester/?url=http://212.232.29.250:8000/live/alisan1234/alisan1234/430.ts&amp;streamtype=TSDOWNLOADER&amp;name=DE: RTL2</link>
</item>

<item>
<title>DE: RTL Crime HD</title>
<link>plugin://plugin.video.f4mTester/?url=http://212.232.29.250:8000/live/alisan1234/alisan1234/394.ts&amp;streamtype=TSDOWNLOADER&amp;name=DE: RTL Crime HD</link>
</item>

<item>
<title>DE: RTL Living HD</title>
<link>plugin://plugin.video.f4mTester/?url=http://212.232.29.250:8000/live/alisan1234/alisan1234/393.ts&amp;streamtype=TSDOWNLOADER&amp;name=DE: RTL Living HD</link>
</item>

<item>
<title>DE: RTL ll You HD</title>
<link>plugin://plugin.video.f4mTester/?url=http://212.232.29.250:8000/live/alisan1234/alisan1234/392.ts&amp;streamtype=TSDOWNLOADER&amp;name=DE: RTL ll You HD</link>
</item>

<item>
<title>DE: RTL Nitro HD</title>
<link>plugin://plugin.video.f4mTester/?url=http://212.232.29.250:8000/live/alisan1234/alisan1234/391.ts&amp;streamtype=TSDOWNLOADER&amp;name=DE: RTL Nitro HD</link>
</item>

<item>
<title>DE: RTL Passion HD</title>
<link>plugin://plugin.video.f4mTester/?url=http://212.232.29.250:8000/live/alisan1234/alisan1234/390.ts&amp;streamtype=TSDOWNLOADER&amp;name=DE: RTL Passion HD</link>
</item>

<item>
<title>DE: SAT.1 HD</title>
<link>plugin://plugin.video.f4mTester/?url=http://212.232.29.250:8000/live/alisan1234/alisan1234/387.ts&amp;streamtype=TSDOWNLOADER&amp;name=DE: SAT.1 HD</link>
</item>

<item>
<title>DE: SAT1</title>
<link>plugin://plugin.video.f4mTester/?url=http://212.232.29.250:8000/live/alisan1234/alisan1234/431.ts&amp;streamtype=TSDOWNLOADER&amp;name=DE: SAT1</link>
</item>

<item>
<title>DE: SAT.1 Emotions HD</title>
<link>plugin://plugin.video.f4mTester/?url=http://212.232.29.250:8000/live/alisan1234/alisan1234/385.ts&amp;streamtype=TSDOWNLOADER&amp;name=DE: SAT.1 Emotions HD</link>
</item>

<item>
<title>DE: SAT.1 Gold HD</title>
<link>plugin://plugin.video.f4mTester/?url=http://212.232.29.250:8000/live/alisan1234/alisan1234/386.ts&amp;streamtype=TSDOWNLOADER&amp;name=DE: SAT.1 Gold HD</link>
</item>

<item>
<title>DE: SAT1 GOLD</title>
<link>plugin://plugin.video.f4mTester/?url=http://212.232.29.250:8000/live/alisan1234/alisan1234/432.ts&amp;streamtype=TSDOWNLOADER&amp;name=DE: SAT1 GOLD</link>
</item>

<item>
<title>DE: ZDF HD</title>
<link>plugin://plugin.video.f4mTester/?url=http://212.232.29.250:8000/live/alisan1234/alisan1234/401.ts&amp;streamtype=TSDOWNLOADER&amp;name=DE: ZDF HD</link>
</item>

<item>
<title>DE: ZDF</title>
<link>plugin://plugin.video.f4mTester/?url=http://212.232.29.250:8000/live/alisan1234/alisan1234/416.ts&amp;streamtype=TSDOWNLOADER&amp;name=DE: ZDF</link>
</item>

<item>
<title>DE: ZDF NEO HD</title>
<link>plugin://plugin.video.f4mTester/?url=http://212.232.29.250:8000/live/alisan1234/alisan1234/400.ts&amp;streamtype=TSDOWNLOADER&amp;name=DE: ZDF NEO HD</link>
</item>

<item>
<title>DE: ZDF NEO</title>
<link>plugin://plugin.video.f4mTester/?url=http://212.232.29.250:8000/live/alisan1234/alisan1234/417.ts&amp;streamtype=TSDOWNLOADER&amp;name=DE: ZDF NEO</link>
</item>

<item>
<title>DE: SERVUS TV HD</title>
<link>plugin://plugin.video.f4mTester/?url=http://212.232.29.250:8000/live/alisan1234/alisan1234/384.ts&amp;streamtype=TSDOWNLOADER&amp;name=DE: SERVUS TV HD</link>
</item>

<item>
<title>DE: VOX HD</title>
<link>plugin://plugin.video.f4mTester/?url=http://212.232.29.250:8000/live/alisan1234/alisan1234/397.ts&amp;streamtype=TSDOWNLOADER&amp;name=DE: VOX HD</link>
</item>

<item>
<title>DE: VOX</title>
<link>plugin://plugin.video.f4mTester/?url=http://212.232.29.250:8000/live/alisan1234/alisan1234/411.ts&amp;streamtype=TSDOWNLOADER&amp;name=DE: VOX</link>
</item>

<item>
<title>DE: ZEE ONE HD</title>
<link>plugin://plugin.video.f4mTester/?url=http://212.232.29.250:8000/live/alisan1234/alisan1234/348.ts&amp;streamtype=TSDOWNLOADER&amp;name=DE: ZEE ONE HD</link>
</item>

<item>
<title>DE: 3SAT HD</title>
<link>plugin://plugin.video.f4mTester/?url=http://212.232.29.250:8000/live/alisan1234/alisan1234/399.ts&amp;streamtype=TSDOWNLOADER&amp;name=DE: 3SAT HD</link>
</item>

<item>
<title>DE: 3Sat</title>
<link>plugin://plugin.video.f4mTester/?url=http://212.232.29.250:8000/live/alisan1234/alisan1234/420.ts&amp;streamtype=TSDOWNLOADER&amp;name=DE: 3Sat</link>
</item>

<item>
<title>DE: VIVA</title>
<link>plugin://plugin.video.f4mTester/?url=http://212.232.29.250:8000/live/alisan1234/alisan1234/423.ts&amp;streamtype=TSDOWNLOADER&amp;name=DE: VIVA</link>
</item>

<item>
<title>DE: 13th Street HD</title>
<link>plugin://plugin.video.f4mTester/?url=http://212.232.29.250:8000/live/alisan1234/alisan1234/366.ts&amp;streamtype=TSDOWNLOADER&amp;name=DE: 13th Street HD</link>
</item>

<item>
<title>DE: ARTE HD</title>
<link>plugin://plugin.video.f4mTester/?url=http://212.232.29.250:8000/live/alisan1234/alisan1234/372.ts&amp;streamtype=TSDOWNLOADER&amp;name=DE: ARTE HD</link>
</item>

<item>
<title>DE: KIKA HD</title>
<link>plugin://plugin.video.f4mTester/?url=http://212.232.29.250:8000/live/alisan1234/alisan1234/376.ts&amp;streamtype=TSDOWNLOADER&amp;name=DE: KIKA HD</link>
</item>

<item>
<title>DE: KIKA</title>
<link>plugin://plugin.video.f4mTester/?url=http://212.232.29.250:8000/live/alisan1234/alisan1234/426.ts&amp;streamtype=TSDOWNLOADER&amp;name=DE: KIKA</link>
</item>

<item>
<title>DE: KINOWELT HD</title>
<link>plugin://plugin.video.f4mTester/?url=http://212.232.29.250:8000/live/alisan1234/alisan1234/375.ts&amp;streamtype=TSDOWNLOADER&amp;name=DE: KINOWELT HD</link>
</item>

<item>
<title>DE: N24 HD</title>
<link>plugin://plugin.video.f4mTester/?url=http://212.232.29.250:8000/live/alisan1234/alisan1234/374.ts&amp;streamtype=TSDOWNLOADER&amp;name=DE: N24 HD</link>
</item>

<item>
<title>DE: N24</title>
<link>plugin://plugin.video.f4mTester/?url=http://212.232.29.250:8000/live/alisan1234/alisan1234/425.ts&amp;streamtype=TSDOWNLOADER&amp;name=DE: N24</link>
</item>

<item>
<title>DE: NTV HD</title>
<link>plugin://plugin.video.f4mTester/?url=http://212.232.29.250:8000/live/alisan1234/alisan1234/368.ts&amp;streamtype=TSDOWNLOADER&amp;name=DE: NTV HD</link>
</item>

<item>
<title>DE: EURONEWS</title>
<link>plugin://plugin.video.f4mTester/?url=http://212.232.29.250:8000/live/alisan1234/alisan1234/347.ts&amp;streamtype=TSDOWNLOADER&amp;name=DE: EURONEWS</link>
</item>

<item>
<title>DE: HEIMATKANAL</title>
<link>plugin://plugin.video.f4mTester/?url=http://212.232.29.250:8000/live/alisan1234/alisan1234/361.ts&amp;streamtype=TSDOWNLOADER&amp;name=DE: HEIMATKANAL</link>
</item>

<item>
<title>DE: ONE HD</title>
<link>plugin://plugin.video.f4mTester/?url=http://212.232.29.250:8000/live/alisan1234/alisan1234/373.ts&amp;streamtype=TSDOWNLOADER&amp;name=DE: ONE HD</link>
</item>

<item>
<title>DE: PHOENIX HD</title>
<link>plugin://plugin.video.f4mTester/?url=http://212.232.29.250:8000/live/alisan1234/alisan1234/370.ts&amp;streamtype=TSDOWNLOADER&amp;name=DE: PHOENIX HD</link>
</item>

<item>
<title>DE: PLANET HD</title>
<link>plugin://plugin.video.f4mTester/?url=http://212.232.29.250:8000/live/alisan1234/alisan1234/369.ts&amp;streamtype=TSDOWNLOADER&amp;name=DE: PLANET HD</link>
</item>

<item>
<title>DE: AXN HD</title>
<link>plugin://plugin.video.f4mTester/?url=http://212.232.29.250:8000/live/alisan1234/alisan1234/371.ts&amp;streamtype=TSDOWNLOADER&amp;name=DE: AXN HD</link>
</item>

<item>
<title>DE: SIXX HD</title>
<link>plugin://plugin.video.f4mTester/?url=http://212.232.29.250:8000/live/alisan1234/alisan1234/383.ts&amp;streamtype=TSDOWNLOADER&amp;name=DE: SIXX HD</link>
</item>

<item>
<title>DE: SRF HD 1</title>
<link>plugin://plugin.video.f4mTester/?url=http://212.232.29.250:8000/live/alisan1234/alisan1234/403.ts&amp;streamtype=TSDOWNLOADER&amp;name=DE: SRF HD 1</link>
</item>

<item>
<title>DE: SRF HD 2</title>
<link>plugin://plugin.video.f4mTester/?url=http://212.232.29.250:8000/live/alisan1234/alisan1234/402.ts&amp;streamtype=TSDOWNLOADER&amp;name=DE: SRF HD 2</link>
</item>

<item>
<title>DE: Romance TV HD</title>
<link>plugin://plugin.video.f4mTester/?url=http://212.232.29.250:8000/live/alisan1234/alisan1234/364.ts&amp;streamtype=TSDOWNLOADER&amp;name=DE: Romance TV HD</link>
</item>

<item>
<title>DE: UNIVERSAL HD</title>
<link>plugin://plugin.video.f4mTester/?url=http://212.232.29.250:8000/live/alisan1234/alisan1234/359.ts&amp;streamtype=TSDOWNLOADER&amp;name=DE: UNIVERSAL HD</link>
</item>

<item>
<title>DE: E! Entertainment</title>
<link>plugin://plugin.video.f4mTester/?url=http://212.232.29.250:8000/live/alisan1234/alisan1234/357.ts&amp;streamtype=TSDOWNLOADER&amp;name=DE: E! Entertainment</link>
</item>

<item>
<title>DE: VIVA/COMEDY CENTRAL HD</title>
<link>plugin://plugin.video.f4mTester/?url=http://212.232.29.250:8000/live/alisan1234/alisan1234/358.ts&amp;streamtype=TSDOWNLOADER&amp;name=DE: VIVA/COMEDY CENTRAL HD</link>
</item>

<item>
<title>DE: SONY Entertainment TV HD</title>
<link>plugin://plugin.video.f4mTester/?url=http://212.232.29.250:8000/live/alisan1234/alisan1234/330.ts&amp;streamtype=TSDOWNLOADER&amp;name=DE: SONY Entertainment TV HD</link>
</item>

<item>
<title>DE: SPIEGEL TV Geschichte</title>
<link>plugin://plugin.video.f4mTester/?url=http://212.232.29.250:8000/live/alisan1234/alisan1234/363.ts&amp;streamtype=TSDOWNLOADER&amp;name=DE: SPIEGEL TV Geschichte</link>
</item>

<item>
<title>DE: SPIEGEL TV Wissen HD</title>
<link>plugin://plugin.video.f4mTester/?url=http://212.232.29.250:8000/live/alisan1234/alisan1234/362.ts&amp;streamtype=TSDOWNLOADER&amp;name=DE: SPIEGEL TV Wissen HD</link>
</item>

<item>
<title>DE: SYFY HD</title>
<link>plugin://plugin.video.f4mTester/?url=http://212.232.29.250:8000/live/alisan1234/alisan1234/329.ts&amp;streamtype=TSDOWNLOADER&amp;name=DE: SYFY HD</link>
</item>

<item>
<title>DE: TELE 5 HD</title>
<link>plugin://plugin.video.f4mTester/?url=http://212.232.29.250:8000/live/alisan1234/alisan1234/360.ts&amp;streamtype=TSDOWNLOADER&amp;name=DE: TELE 5 HD</link>
</item>

<item>
<title>DE: TLC HD</title>
<link>plugin://plugin.video.f4mTester/?url=http://212.232.29.250:8000/live/alisan1234/alisan1234/325.ts&amp;streamtype=TSDOWNLOADER&amp;name=DE: TLC HD</link>
</item>

<item>
<title>DE: TNT Comedy HD</title>
<link>plugin://plugin.video.f4mTester/?url=http://212.232.29.250:8000/live/alisan1234/alisan1234/326.ts&amp;streamtype=TSDOWNLOADER&amp;name=DE: TNT Comedy HD</link>
</item>

<item>
<title>DE: TNT Film HD</title>
<link>plugin://plugin.video.f4mTester/?url=http://212.232.29.250:8000/live/alisan1234/alisan1234/327.ts&amp;streamtype=TSDOWNLOADER&amp;name=DE: TNT Film HD</link>
</item>

<item>
<title>DE: TNT Serie HD</title>
<link>plugin://plugin.video.f4mTester/?url=http://212.232.29.250:8000/live/alisan1234/alisan1234/328.ts&amp;streamtype=TSDOWNLOADER&amp;name=DE: TNT Serie HD</link>
</item>

<item>
<title>DE: DISNEY Channel HD</title>
<link>plugin://plugin.video.f4mTester/?url=http://212.232.29.250:8000/live/alisan1234/alisan1234/355.ts&amp;streamtype=TSDOWNLOADER&amp;name=DE: DISNEY Channel HD</link>
</item>

<item>
<title>DE: DISNEY Cinemagic HD</title>
<link>plugin://plugin.video.f4mTester/?url=http://212.232.29.250:8000/live/alisan1234/alisan1234/354.ts&amp;streamtype=TSDOWNLOADER&amp;name=DE: DISNEY Cinemagic HD</link>
</item>

<item>
<title>DE: DISNEY Jr. HD</title>
<link>plugin://plugin.video.f4mTester/?url=http://212.232.29.250:8000/live/alisan1234/alisan1234/353.ts&amp;streamtype=TSDOWNLOADER&amp;name=DE: DISNEY Jr. HD</link>
</item>

<item>
<title>DE: DISNEY XD HD</title>
<link>plugin://plugin.video.f4mTester/?url=http://212.232.29.250:8000/live/alisan1234/alisan1234/352.ts&amp;streamtype=TSDOWNLOADER&amp;name=DE: DISNEY XD HD</link>
</item>

<item>
<title>DE: JUNIOR [6:00-20:00]</title>
<link>plugin://plugin.video.f4mTester/?url=http://212.232.29.250:8000/live/alisan1234/alisan1234/349.ts&amp;streamtype=TSDOWNLOADER&amp;name=DE: JUNIOR [6:00-20:00]</link>
</item>

<item>
<title>DE: NICK Jr. HD</title>
<link>plugin://plugin.video.f4mTester/?url=http://212.232.29.250:8000/live/alisan1234/alisan1234/351.ts&amp;streamtype=TSDOWNLOADER&amp;name=DE: NICK Jr. HD</link>
</item>

<item>
<title>DE: NICKELODEON HD</title>
<link>plugin://plugin.video.f4mTester/?url=http://212.232.29.250:8000/live/alisan1234/alisan1234/350.ts&amp;streamtype=TSDOWNLOADER&amp;name=DE: NICKELODEON HD</link>
</item>

<item>
<title>DE: TOGGO Plus</title>
<link>plugin://plugin.video.f4mTester/?url=http://212.232.29.250:8000/live/alisan1234/alisan1234/388.ts&amp;streamtype=TSDOWNLOADER&amp;name=DE: TOGGO Plus</link>
</item>

<item>
<title>DE: Nickelodeon</title>
<link>plugin://plugin.video.f4mTester/?url=http://212.232.29.250:8000/live/alisan1234/alisan1234/427.ts&amp;streamtype=TSDOWNLOADER&amp;name=DE: Nickelodeon</link>
</item>

<item>
<title>DE: CARTOON NETWORK HD</title>
<link>plugin://plugin.video.f4mTester/?url=http://212.232.29.250:8000/live/alisan1234/alisan1234/356.ts&amp;streamtype=TSDOWNLOADER&amp;name=DE: CARTOON NETWORK HD</link>
</item>

<item>
<title>DE: BOOMERANG HD</title>
<link>plugin://plugin.video.f4mTester/?url=http://212.232.29.250:8000/live/alisan1234/alisan1234/367.ts&amp;streamtype=TSDOWNLOADER&amp;name=DE: BOOMERANG HD</link>
</item>

<item>
<title>DE: DMAX HD</title>
<link>plugin://plugin.video.f4mTester/?url=http://212.232.29.250:8000/live/alisan1234/alisan1234/398.ts&amp;streamtype=TSDOWNLOADER&amp;name=DE: DMAX HD</link>
</item>

<item>
<title>DE: DMAX</title>
<link>plugin://plugin.video.f4mTester/?url=http://212.232.29.250:8000/live/alisan1234/alisan1234/419.ts&amp;streamtype=TSDOWNLOADER&amp;name=DE: DMAX</link>
</item>

<item>
<title>DE: NAT GEO HD</title>
<link>plugin://plugin.video.f4mTester/?url=http://212.232.29.250:8000/live/alisan1234/alisan1234/298.ts&amp;streamtype=TSDOWNLOADER&amp;name=DE: NAT GEO HD</link>
</item>

<item>
<title>DE: NAT GEO People HD</title>
<link>plugin://plugin.video.f4mTester/?url=http://212.232.29.250:8000/live/alisan1234/alisan1234/297.ts&amp;streamtype=TSDOWNLOADER&amp;name=DE: NAT GEO People HD</link>
</item>

<item>
<title>DE: NAT GEO Wild HD</title>
<link>plugin://plugin.video.f4mTester/?url=http://212.232.29.250:8000/live/alisan1234/alisan1234/296.ts&amp;streamtype=TSDOWNLOADER&amp;name=DE: NAT GEO Wild HD</link>
</item>

<item>
<title>DE: DISCOVERY Channel HD</title>
<link>plugin://plugin.video.f4mTester/?url=http://212.232.29.250:8000/live/alisan1234/alisan1234/294.ts&amp;streamtype=TSDOWNLOADER&amp;name=DE: DISCOVERY Channel HD</link>
</item>

<item>
<title>DE: HISTORY Channel HD</title>
<link>plugin://plugin.video.f4mTester/?url=http://212.232.29.250:8000/live/alisan1234/alisan1234/293.ts&amp;streamtype=TSDOWNLOADER&amp;name=DE: HISTORY Channel HD</link>
</item>

<item>
<title>DE: ANIMAL Planet HD</title>
<link>plugin://plugin.video.f4mTester/?url=http://212.232.29.250:8000/live/alisan1234/alisan1234/295.ts&amp;streamtype=TSDOWNLOADER&amp;name=DE: ANIMAL Planet HD</link>
</item>

<item>
<title>DE: SKY STORE 1</title>
<link>plugin://plugin.video.f4mTester/?url=http://212.232.29.250:8000/live/alisan1234/alisan1234/2829.ts&amp;streamtype=TSDOWNLOADER&amp;name=DE: SKY STORE 1</link>
</item>

<item>
<title>DE: SKY STORE 2</title>
<link>plugin://plugin.video.f4mTester/?url=http://212.232.29.250:8000/live/alisan1234/alisan1234/2828.ts&amp;streamtype=TSDOWNLOADER&amp;name=DE: SKY STORE 2</link>
</item>

<item>
<title>DE: SKY STORE 3</title>
<link>plugin://plugin.video.f4mTester/?url=http://212.232.29.250:8000/live/alisan1234/alisan1234/2827.ts&amp;streamtype=TSDOWNLOADER&amp;name=DE: SKY STORE 3</link>
</item>

<item>
<title>DE: SKY STORE 4</title>
<link>plugin://plugin.video.f4mTester/?url=http://212.232.29.250:8000/live/alisan1234/alisan1234/2826.ts&amp;streamtype=TSDOWNLOADER&amp;name=DE: SKY STORE 4</link>
</item>

<item>
<title>DE: SKY STORE 5</title>
<link>plugin://plugin.video.f4mTester/?url=http://212.232.29.250:8000/live/alisan1234/alisan1234/2825.ts&amp;streamtype=TSDOWNLOADER&amp;name=DE: SKY STORE 5</link>
</item>

<item>
<title>DE: SKY STORE 6</title>
<link>plugin://plugin.video.f4mTester/?url=http://212.232.29.250:8000/live/alisan1234/alisan1234/2824.ts&amp;streamtype=TSDOWNLOADER&amp;name=DE: SKY STORE 6</link>
</item>

<item>
<title>DE: SKY STORE 7</title>
<link>plugin://plugin.video.f4mTester/?url=http://212.232.29.250:8000/live/alisan1234/alisan1234/2823.ts&amp;streamtype=TSDOWNLOADER&amp;name=DE: SKY STORE 7</link>
</item>

<item>
<title>DE: SKY STORE 8</title>
<link>plugin://plugin.video.f4mTester/?url=http://212.232.29.250:8000/live/alisan1234/alisan1234/2822.ts&amp;streamtype=TSDOWNLOADER&amp;name=DE: SKY STORE 8</link>
</item>

<item>
<title>DE: SKY STORE 9</title>
<link>plugin://plugin.video.f4mTester/?url=http://212.232.29.250:8000/live/alisan1234/alisan1234/2821.ts&amp;streamtype=TSDOWNLOADER&amp;name=DE: SKY STORE 9</link>
</item>

<item>
<title>DE: SKY STORE 10</title>
<link>plugin://plugin.video.f4mTester/?url=http://212.232.29.250:8000/live/alisan1234/alisan1234/2820.ts&amp;streamtype=TSDOWNLOADER&amp;name=DE: SKY STORE 10</link>
</item>

<item>
<title>DE: SKY 1 HD</title>
<link>plugin://plugin.video.f4mTester/?url=http://212.232.29.250:8000/live/alisan1234/alisan1234/343.ts&amp;streamtype=TSDOWNLOADER&amp;name=DE: SKY 1 HD</link>
</item>

<item>
<title>DE: SKY CINEMA HD</title>
<link>plugin://plugin.video.f4mTester/?url=http://212.232.29.250:8000/live/alisan1234/alisan1234/342.ts&amp;streamtype=TSDOWNLOADER&amp;name=DE: SKY CINEMA HD</link>
</item>

<item>
<title>DE: SKY CINEMA 1 HD</title>
<link>plugin://plugin.video.f4mTester/?url=http://212.232.29.250:8000/live/alisan1234/alisan1234/341.ts&amp;streamtype=TSDOWNLOADER&amp;name=DE: SKY CINEMA 1 HD</link>
</item>

<item>
<title>DE: SKY CINEMA 24 HD</title>
<link>plugin://plugin.video.f4mTester/?url=http://212.232.29.250:8000/live/alisan1234/alisan1234/340.ts&amp;streamtype=TSDOWNLOADER&amp;name=DE: SKY CINEMA 24 HD</link>
</item>

<item>
<title>DE: SKY CINEMA FAMILY HD</title>
<link>plugin://plugin.video.f4mTester/?url=http://212.232.29.250:8000/live/alisan1234/alisan1234/339.ts&amp;streamtype=TSDOWNLOADER&amp;name=DE: SKY CINEMA FAMILY HD</link>
</item>

<item>
<title>DE: SKY COMEDY</title>
<link>plugin://plugin.video.f4mTester/?url=http://212.232.29.250:8000/live/alisan1234/alisan1234/337.ts&amp;streamtype=TSDOWNLOADER&amp;name=DE: SKY COMEDY</link>
</item>

<item>
<title>DE: SKY EMOTION</title>
<link>plugin://plugin.video.f4mTester/?url=http://212.232.29.250:8000/live/alisan1234/alisan1234/336.ts&amp;streamtype=TSDOWNLOADER&amp;name=DE: SKY EMOTION</link>
</item>

<item>
<title>DE: SKY HITS HD</title>
<link>plugin://plugin.video.f4mTester/?url=http://212.232.29.250:8000/live/alisan1234/alisan1234/335.ts&amp;streamtype=TSDOWNLOADER&amp;name=DE: SKY HITS HD</link>
</item>

<item>
<title>DE: SKY KRIMI</title>
<link>plugin://plugin.video.f4mTester/?url=http://212.232.29.250:8000/live/alisan1234/alisan1234/332.ts&amp;streamtype=TSDOWNLOADER&amp;name=DE: SKY KRIMI</link>
</item>

<item>
<title>DE: SKY NOSTALGIE</title>
<link>plugin://plugin.video.f4mTester/?url=http://212.232.29.250:8000/live/alisan1234/alisan1234/334.ts&amp;streamtype=TSDOWNLOADER&amp;name=DE: SKY NOSTALGIE</link>
</item>

<item>
<title>DE: SKY ACTION HD</title>
<link>plugin://plugin.video.f4mTester/?url=http://212.232.29.250:8000/live/alisan1234/alisan1234/338.ts&amp;streamtype=TSDOWNLOADER&amp;name=DE: SKY ACTION HD</link>
</item>

<item>
<title>DE: SKY ATLANTIC HD</title>
<link>plugin://plugin.video.f4mTester/?url=http://212.232.29.250:8000/live/alisan1234/alisan1234/333.ts&amp;streamtype=TSDOWNLOADER&amp;name=DE: SKY ATLANTIC HD</link>
</item>

<item>
<title>DE: SKY Bundesliga 1 HD [24/7]</title>
<link>plugin://plugin.video.f4mTester/?url=http://212.232.29.250:8000/live/alisan1234/alisan1234/312.ts&amp;streamtype=TSDOWNLOADER&amp;name=DE: SKY Bundesliga 1 HD [24/7]</link>
</item>

<item>
<title>DE: SKY Bundesliga 2 HD</title>
<link>plugin://plugin.video.f4mTester/?url=http://212.232.29.250:8000/live/alisan1234/alisan1234/311.ts&amp;streamtype=TSDOWNLOADER&amp;name=DE: SKY Bundesliga 2 HD</link>
</item>

<item>
<title>DE: SKY Bundesliga 3 HD</title>
<link>plugin://plugin.video.f4mTester/?url=http://212.232.29.250:8000/live/alisan1234/alisan1234/310.ts&amp;streamtype=TSDOWNLOADER&amp;name=DE: SKY Bundesliga 3 HD</link>
</item>

<item>
<title>DE: SKY Bundesliga 4 HD</title>
<link>plugin://plugin.video.f4mTester/?url=http://212.232.29.250:8000/live/alisan1234/alisan1234/309.ts&amp;streamtype=TSDOWNLOADER&amp;name=DE: SKY Bundesliga 4 HD</link>
</item>

<item>
<title>DE: SKY Bundesliga 5</title>
<link>plugin://plugin.video.f4mTester/?url=http://212.232.29.250:8000/live/alisan1234/alisan1234/308.ts&amp;streamtype=TSDOWNLOADER&amp;name=DE: SKY Bundesliga 5</link>
</item>

<item>
<title>DE: SKY Bundesliga 6</title>
<link>plugin://plugin.video.f4mTester/?url=http://212.232.29.250:8000/live/alisan1234/alisan1234/307.ts&amp;streamtype=TSDOWNLOADER&amp;name=DE: SKY Bundesliga 6</link>
</item>

<item>
<title>DE: SKY Bundesliga 7</title>
<link>plugin://plugin.video.f4mTester/?url=http://212.232.29.250:8000/live/alisan1234/alisan1234/306.ts&amp;streamtype=TSDOWNLOADER&amp;name=DE: SKY Bundesliga 7</link>
</item>

<item>
<title>DE: SKY Bundesliga 8</title>
<link>plugin://plugin.video.f4mTester/?url=http://212.232.29.250:8000/live/alisan1234/alisan1234/305.ts&amp;streamtype=TSDOWNLOADER&amp;name=DE: SKY Bundesliga 8</link>
</item>

<item>
<title>DE: SKY Bundesliga 9</title>
<link>plugin://plugin.video.f4mTester/?url=http://212.232.29.250:8000/live/alisan1234/alisan1234/304.ts&amp;streamtype=TSDOWNLOADER&amp;name=DE: SKY Bundesliga 9</link>
</item>

<item>
<title>DE: SKY Bundesliga 10</title>
<link>plugin://plugin.video.f4mTester/?url=http://212.232.29.250:8000/live/alisan1234/alisan1234/303.ts&amp;streamtype=TSDOWNLOADER&amp;name=DE: SKY Bundesliga 10</link>
</item>

<item>
<title>DE: SKY Sport 1 HD [24/7]</title>
<link>plugin://plugin.video.f4mTester/?url=http://212.232.29.250:8000/live/alisan1234/alisan1234/323.ts&amp;streamtype=TSDOWNLOADER&amp;name=DE: SKY Sport 1 HD [24/7]</link>
</item>

<item>
<title>DE: SKY Sport 2 HD [24/7]</title>
<link>plugin://plugin.video.f4mTester/?url=http://212.232.29.250:8000/live/alisan1234/alisan1234/322.ts&amp;streamtype=TSDOWNLOADER&amp;name=DE: SKY Sport 2 HD [24/7]</link>
</item>

<item>
<title>DE: SKY Sport 3 HD</title>
<link>plugin://plugin.video.f4mTester/?url=http://212.232.29.250:8000/live/alisan1234/alisan1234/321.ts&amp;streamtype=TSDOWNLOADER&amp;name=DE: SKY Sport 3 HD</link>
</item>

<item>
<title>DE: SKY Sport 4 HD</title>
<link>plugin://plugin.video.f4mTester/?url=http://212.232.29.250:8000/live/alisan1234/alisan1234/320.ts&amp;streamtype=TSDOWNLOADER&amp;name=DE: SKY Sport 4 HD</link>
</item>

<item>
<title>DE: SKY Sport 5 HD</title>
<link>plugin://plugin.video.f4mTester/?url=http://212.232.29.250:8000/live/alisan1234/alisan1234/319.ts&amp;streamtype=TSDOWNLOADER&amp;name=DE: SKY Sport 5 HD</link>
</item>

<item>
<title>DE: SKY Sport 6</title>
<link>plugin://plugin.video.f4mTester/?url=http://212.232.29.250:8000/live/alisan1234/alisan1234/318.ts&amp;streamtype=TSDOWNLOADER&amp;name=DE: SKY Sport 6</link>
</item>

<item>
<title>DE: SKY Sport 7</title>
<link>plugin://plugin.video.f4mTester/?url=http://212.232.29.250:8000/live/alisan1234/alisan1234/317.ts&amp;streamtype=TSDOWNLOADER&amp;name=DE: SKY Sport 7</link>
</item>

<item>
<title>DE: SKY Sport 8</title>
<link>plugin://plugin.video.f4mTester/?url=http://212.232.29.250:8000/live/alisan1234/alisan1234/316.ts&amp;streamtype=TSDOWNLOADER&amp;name=DE: SKY Sport 8</link>
</item>

<item>
<title>DE: SKY Sport 9</title>
<link>plugin://plugin.video.f4mTester/?url=http://212.232.29.250:8000/live/alisan1234/alisan1234/315.ts&amp;streamtype=TSDOWNLOADER&amp;name=DE: SKY Sport 9</link>
</item>

<item>
<title>DE: SKY Sport 10</title>
<link>plugin://plugin.video.f4mTester/?url=http://212.232.29.250:8000/live/alisan1234/alisan1234/314.ts&amp;streamtype=TSDOWNLOADER&amp;name=DE: SKY Sport 10</link>
</item>

<item>
<title>DE: SKY Sport Austria HD</title>
<link>plugin://plugin.video.f4mTester/?url=http://212.232.29.250:8000/live/alisan1234/alisan1234/313.ts&amp;streamtype=TSDOWNLOADER&amp;name=DE: SKY Sport Austria HD</link>
</item>

<item>
<title>DE: SKY Sports News HD</title>
<link>plugin://plugin.video.f4mTester/?url=http://212.232.29.250:8000/live/alisan1234/alisan1234/324.ts&amp;streamtype=TSDOWNLOADER&amp;name=DE: SKY Sports News HD</link>
</item>

<item>
<title>DE: SPORT 1</title>
<link>plugin://plugin.video.f4mTester/?url=http://212.232.29.250:8000/live/alisan1234/alisan1234/301.ts&amp;streamtype=TSDOWNLOADER&amp;name=DE: SPORT 1</link>
</item>

<item>
<title>DE: SPORT 1 HD</title>
<link>plugin://plugin.video.f4mTester/?url=http://212.232.29.250:8000/live/alisan1234/alisan1234/302.ts&amp;streamtype=TSDOWNLOADER&amp;name=DE: SPORT 1 HD</link>
</item>

<item>
<title>DE: SPORT 1 US HD</title>
<link>plugin://plugin.video.f4mTester/?url=http://212.232.29.250:8000/live/alisan1234/alisan1234/300.ts&amp;streamtype=TSDOWNLOADER&amp;name=DE: SPORT 1 US HD</link>
</item>

<item>
<title>DE: SPORT DIGITAL HD</title>
<link>plugin://plugin.video.f4mTester/?url=http://212.232.29.250:8000/live/alisan1234/alisan1234/299.ts&amp;streamtype=TSDOWNLOADER&amp;name=DE: SPORT DIGITAL HD</link>
</item>

<item>
<title>DE: EUROSPORT 1 HD</title>
<link>plugin://plugin.video.f4mTester/?url=http://212.232.29.250:8000/live/alisan1234/alisan1234/346.ts&amp;streamtype=TSDOWNLOADER&amp;name=DE: EUROSPORT 1 HD</link>
</item>

<item>
<title>DE: Eurosport</title>
<link>plugin://plugin.video.f4mTester/?url=http://212.232.29.250:8000/live/alisan1234/alisan1234/422.ts&amp;streamtype=TSDOWNLOADER&amp;name=DE: Eurosport</link>
</item>

<item>
<title>DE: EUROSPORT 2</title>
<link>plugin://plugin.video.f4mTester/?url=http://212.232.29.250:8000/live/alisan1234/alisan1234/345.ts&amp;streamtype=TSDOWNLOADER&amp;name=DE: EUROSPORT 2</link>
</item>

<item>
<title>DE: EUROSPORT 2 XTRA</title>
<link>plugin://plugin.video.f4mTester/?url=http://212.232.29.250:8000/live/alisan1234/alisan1234/344.ts&amp;streamtype=TSDOWNLOADER&amp;name=DE: EUROSPORT 2 XTRA</link>
</item>

<item>
<title>DE: Auto Motor Sport Channel HD</title>
<link>plugin://plugin.video.f4mTester/?url=http://212.232.29.250:8000/live/alisan1234/alisan1234/365.ts&amp;streamtype=TSDOWNLOADER&amp;name=DE: Auto Motor Sport Channel HD</link>
</item>
